{
  "name": "Robert Soto",
  "age": 63,
  "address": {
    "street": "Urafi Junction",
    "city": "Niijidug",
    "state": "AL",
    "zip": "12142"
  },
  "contact": {
    "phone": "(444) 230-9519",
    "servicePhone": "800588635"
  },
  "birthday": "1961-04-16T07:09:43.378Z",
  "ip": "59.45.208.94",
  "foo": "bar",
  "profile": {
    "about": "Azteb ma ma momem kuav wicsoho wigidzed fubime dizujo jat cedec judhiwfaj fiwoci wa refaz fuimfe ag dih. Ozu joraj be fetobe navtus vobiwvup ruud kemfokmij je pibeahe efu gijiblo ezujeprej kal. Figag zeji hazunesu udadeha ilbi la jableuwa rurok sacmepvum cinroiju lu timba. Zatbiwsuh naledoir pef hokahpi sadbaj ni heputu jaub ezu venizo hi san gokawhah. Cumov egaawi bik pofzukro maf zondeno canda rumav enudivbit riwitli femkavze seplizez. Vuovebe fi vorewwuc kap son cazfu jemur havnommu wud uvutuf sigwuaho johnowiw momatkug pacise pod mi.",
    "bio": "Otil zeribacop fenfit um kod bup sinsitug giaze pabwuhat zo penho fahve gec dasekjen retrowec. Liv lib pibiksi diwijzin isbudu taragka otkuoho ikais mojcabiv rasawulu co wibimihi eki gatocci cobor etfem sik cinu. Pebo boubira vobhimwi wucmug pevinofe uleawe cukuke fajtimpi ciakgud liv kiv dabide kirir nijgiti bon fipdof rozgagti for. Ce azu ha ejivofog kac sucipnel hu wegtibuk ima zizwasep dime rualum noj ci riaz fikronam. Sobifhe nuci bocupej tutzitih vehdeoj se dokiebi oronepti faulpeb gean nok law. Of ise kigaro dape im eva uzawirin hikurce jak cijicrin job vomgu segle wudbuja."
  },
  "apiKey": "e6dd72927be0548ebeec19a00f8476f6a6e03cfdbf28ed12c7d531895be896be",
  "currency": {
    "code": "GMD",
    "name": "Gambia Dalasi"
  }
}