{
  "name": "Ada Moreno",
  "age": 36,
  "address": {
    "street": "Dihip Heights",
    "city": "Cokiceku",
    "state": "WV",
    "zip": "61193"
  },
  "contact": {
    "phone": "(615) 435-6347",
    "servicePhone": "800461741"
  },
  "birthday": "1976-01-18T01:12:08.983Z",
  "ip": "227.67.9.216",
  "foo": "bar",
  "profile": {
    "about": "Vaih cualov utaifo uc totaczu regtiigi se civozubaz jeh ascuzuv iranina ru otlolul foztasfob tuzbolwah vi suvburgu. Rur dafle serafa to sos cirmed sohuh bu ahjus si remo juuwuev zipjar vimeb armam tec je rus. Noziw ubazazni uv zonwo docgi rol owoepiz uwi vec zuzorvir pabud ire uwki biiw wuj woadevi.",
    "bio": "Govkobaz tospo faadzih fiz ogo hufhum lum rigetsub hekbabud riwusvid dum agpelsel ca jahpifu me. Ka to rek wutjogvit octuzo luiba muwkooj helafbe ogunup suwod ur fe foja gorehkep jinsuz hibtotjoc zewodow. Pepjamfe re etigi jisitel omsu gokcum akapilmu ugoihfi bazew wotfag azje nezi oc henwabuc. Husippi kimbid lum hivurubi vupvubofa boobu ze gowcona us jajnoifi zid ejci gu fuz ba pehaku ceari mi."
  },
  "apiKey": "a290aaa584b896a330deb420c006a79e117b451fb7e446cdb1208e2592a0436f",
  "currency": {
    "code": "NOK",
    "name": "Norway Krone"
  }
}