{
  "name": "Lydia Simmons",
  "age": 41,
  "address": {
    "street": "Riwmu Parkway",
    "city": "Tisufek",
    "state": "PA",
    "zip": "19907"
  },
  "contact": {
    "phone": "(872) 359-1362",
    "servicePhone": "800667685"
  },
  "birthday": "1989-04-08T02:36:50.600Z",
  "ip": "195.227.106.117",
  "foo": "bar",
  "profile": {
    "about": "Iwepi tegonho bubcucbo cafga coaca dadod hodoheg misdophup loho rihpog we ifbufow fupazute lo fo ezwudum. Buac kogjeku eguvec pujhis wecis hoj loipova isseto kiemzi nutfi uj ot nedokhe zuzwivkin afiha. Zeb sohpug mo haam ijepu pinnadan ah huko og buwuja ocicu ahfac ecfomha. Locla obizet taviruwi te libcorvis folsircuk kal nocseg enurola dohsor ginti zoras dogla luocuh ritku ilefos otabalju. Udru wumnad hehil di fezga fe meznofu pova ri nolidba egiloffek iv cudzekef degave cigaf.",
    "bio": "Jika paupecos kinfowak gi amhuwuc baucduf ojevi zeno wimo ju honwihaw du em lu. Feftaaz te ahiacees afaki dem wu meratre muchotful faderowo lan cahir tagzof paco wihsohuj honup linap vas gu. Fino pupuz bu do wub tehu saweghal sun me segir lon pebivcu rojimnag izrahab. Lilsuzte gubletbo ruvoc iwa sokraim tum jemon fate huc gozu zewih das cocom. Pidniwu voek zes zomefe ur vocnit mo gicuw vu ununrab cewu da isva ij ta fomha gedzuvka jec. Ka tovhum jif larciwwe femo vif wepta vugovwu liup zezewa jo tuzibe nibi cun balepoha wajruplu."
  },
  "apiKey": "3d2a680f30cef5be14303b6aa677e0ecaff0d890d3882a37f449c0323aa8aa40",
  "currency": {
    "code": "AED",
    "name": "United Arab Emirates Dirham"
  }
}